dynata_rex/__init__.py
dynata_rex/exceptions.py
dynata_rex/helpers.py
dynata_rex/logs.py
dynata_rex/opportunity_registry.py
dynata_rex/respondent_gateway.py
dynata_rex/signer.py
dynata_rex/models/__init__.py
dynata_rex/models/base.py
dynata_rex/models/opportunity_registry.py
dynata_rex/models/respondent_gateway.py
examples/__init__.py
examples/opportunity_registry/01_instantiate_client.py
examples/opportunity_registry/02_receive_notifications.py
examples/opportunity_registry/03_convert_opportunity_json.py
examples/opportunity_registry/04_acknowledge_multiple_notifications.py
examples/opportunity_registry/05_acknowledge_single_notification.py
examples/opportunity_registry/06_list_corresponding_opportunities_by_project.py
examples/opportunity_registry/07_download_collection_type_cell.py
examples/opportunity_registry/__init__.py
examples/respondent_gateway/01_instantiate_client.py
examples/respondent_gateway/02_create_signed_link.py
examples/respondent_gateway/03_create_quoted_signed_link.py
examples/respondent_gateway/04_create_survey_link_for_panelist.py
examples/respondent_gateway/05_create_survey_link_for_panelist_with_custom_parameters.py
examples/respondent_gateway/06_verify_signed_url.py
examples/respondent_gateway/07_get_end_link_disposition.py
examples/respondent_gateway/08_create_context.py
examples/respondent_gateway/09_retrieve_context.py
examples/respondent_gateway/10_expire_context.py
examples/respondent_gateway/11_list_attributes.py
examples/respondent_gateway/12_get_attribute_info.py
examples/respondent_gateway/__init__.py
dynata_rex-1.3.1.dist-info/LICENSE
dynata_rex-1.3.1.dist-info/METADATA
dynata_rex-1.3.1.dist-info/WHEEL
dynata_rex-1.3.1.dist-info/top_level.txt
dynata_rex-1.3.1.dist-info/RECORD
