Metadata-Version: 2.1
Name: dynata-rex
Version: 1.3.1
Summary: Package for building and interacting with the Dynata Respondent Exchange (REX)
Home-page: https://github.com/dynata/rex-sdk-python
Author: REX Maintainers
Author-email: tech.supply@Dynata.com
Keywords: respondent exchange rex smor dynata python
Platform: Any
Classifier: Programming Language :: Python
Classifier: Programming Language :: Python :: 3
Classifier: Programming Language :: Python :: 3.6
Classifier: Programming Language :: Python :: 3.7
Classifier: Programming Language :: Python :: 3.8
Classifier: Programming Language :: Python :: 3.9
Classifier: Programming Language :: Python :: 3.10
License-File: LICENSE
Requires-Dist: requests (==2.27.1)
Requires-Dist: pydantic (==1.8.2)
Requires-Dist: typing-extensions (==4.7.1) ; python_version == "3.6"
Requires-Dist: dataclasses (==0.8) ; python_version == "3.6"
Requires-Dist: typing-extensions (==4.7.1) ; python_version == "3.7"
Provides-Extra: testing
Requires-Dist: pytest ; extra == 'testing'
